tkitCache/Cache.py
tkitCache/__init__.py
tkitCache-0.0.1.120220108163426.dist-info/LICENSE
tkitCache-0.0.1.120220108163426.dist-info/METADATA
tkitCache-0.0.1.120220108163426.dist-info/WHEEL
tkitCache-0.0.1.120220108163426.dist-info/top_level.txt
tkitCache-0.0.1.120220108163426.dist-info/RECORD
