Metadata-Version: 2.1
Name: tkitCache
Version: 0.0.1.120220108163426
Summary: Terry toolkit tkitCache
Home-page: https://github.com/napoler/tkitCache/
Author: Terry Chan
Author-email: napoler2008@gmail.com
License: UNKNOWN
Platform: UNKNOWN
Requires-Dist: cacheout (==0.13.1)
